watchmap-sdk/__init__.py
watchmap-sdk/main.py
watchmap_sdk/__init__.py
watchmap_sdk/main.py
watchmap_sdk-0.1.0.dist-info/METADATA
watchmap_sdk-0.1.0.dist-info/WHEEL
watchmap_sdk-0.1.0.dist-info/top_level.txt
watchmap_sdk-0.1.0.dist-info/RECORD
