Metadata-Version: 2.1
Name: watchmap-sdk
Version: 0.1.0
Summary: A Python package to watch a directory and map its contents to a dictionary.
Home-page: UNKNOWN
Author: Me
License: MIT
Platform: UNKNOWN
